mangas_origines/__init__.py
mangas_origines/auth.py
mangas_origines/mangas_origines.py
mangas_origines/utils.py
mangas_origines/exceptions/__init__.py
mangas_origines/exceptions/exceptions.py
mangas_origines/objects/__init__.py
mangas_origines/objects/chapter.py
mangas_origines/objects/comment.py
mangas_origines/objects/favorite.py
mangas_origines/objects/scan.py
mangas_origines/script/__init__.py
mangas_origines/script/arguments_builder.py
mangas_origines/script/cursor.py
mangas_origines/script/mangas_origines_script.py
mangas_origines/script/progress_bar.py
mangas_origines/script/spinner.py
mangas_origines/script/start.py
MangasOrigines-0.0.8.dist-info/LICENSE
MangasOrigines-0.0.8.dist-info/METADATA
MangasOrigines-0.0.8.dist-info/WHEEL
MangasOrigines-0.0.8.dist-info/entry_points.txt
MangasOrigines-0.0.8.dist-info/top_level.txt
MangasOrigines-0.0.8.dist-info/RECORD
