Metadata-Version: 2.1
Name: MangasOrigines
Version: 0.0.8
Summary: An API wrapper for MangasOrigines written in Python.
Home-page: https://github.com/Asthowen/MangasOriginesDownloader
Author: Asthowen
Author-email: contact@asthowen.fr
License: GNU v3.0
Platform: UNKNOWN
Requires-Python: >= 3.6
License-File: LICENSE
Requires-Dist: aiohttp
Requires-Dist: aiofiles
Requires-Dist: beautifulsoup4
Requires-Dist: setproctitle
